setup.cfg
setup.py
test/test_braille.py
test/test_commands.py
test/test_grid.py
test/test_util.py
tulip/__init__.py
tulip/braille.py
tulip/grid.py
tulip/image.py
tulip/util.py
tulip_images.egg-info/PKG-INFO
tulip_images.egg-info/SOURCES.txt
tulip_images.egg-info/dependency_links.txt
tulip_images.egg-info/entry_points.txt
tulip_images.egg-info/requires.txt
tulip_images.egg-info/top_level.txt