Metadata-Version: 1.1
Name: tulip-images
Version: 0.1
Summary: Display simple images in your terminal
Home-page: UNKNOWN
Author: Braulio Valdivielso
Author-email: yosoy@braulio.me
License: UNKNOWN
Platform: UNKNOWN
Classifier: Programming Language :: Python :: 3
